{"parent":"page.promotion-2025-10.json","context":{"market":"france"},"sections":{"collapsible_tabs_qETzUn":{"settings":{},"blocks":{"question_qVQbXG":{"settings":{"answer_de":"<p>A: Yes! We offer convenient installment payment options through several partners:<\/p><p>Alma: 2–4 months interest-free<br\/>Klarna: 3 months interest-free<br\/><br\/>Simply add your chosen E-Bike to the cart and select your preferred payment method at checkout.<\/p>","answer_fr":"<p>R : Oui ! Nous proposons des options de paiement en plusieurs fois grâce à nos partenaires suivants :<\/p><p>Alma : 2 à 4 mois sans frais<br\/>Klarna : 3 mois sans frais<br\/><br\/>Il vous suffit d’ajouter le vélo électrique de votre choix au panier et de sélectionner votre mode de paiement préféré lors du passage à la caisse.<\/p>"}}}},"adaptive_content_grid_dTa7LW":{"settings":{},"blocks":{},"block_order":["collection_block_7KF3JH","custom_block_rRMGDU","custom_block_iW7J3C"]}}}